atools/__init__.py
atools/cli.py
atools/subcommands/__init__.py
atools/subcommands/ipinfo.py
atools/subcommands/linecounter.py
atools/subcommands/portcheck.py
atools_cli-0.1.0.dist-info/LICENSE
atools_cli-0.1.0.dist-info/METADATA
atools_cli-0.1.0.dist-info/WHEEL
atools_cli-0.1.0.dist-info/entry_points.txt
atools_cli-0.1.0.dist-info/top_level.txt
atools_cli-0.1.0.dist-info/RECORD
