Metadata-Version: 2.2
Name: atools-cli
Version: 0.1.0
Summary: Arne's CLI Tools
Author-email: Arne Van Looveren <arne@arnevanlooveren.be>
License: MIT License
License-File: LICENSE
Requires-Dist: requests
